nyanger/__init__.py
nyanger/asynchronous/__init__.py
nyanger/asynchronous/nyan.py
nyanger/asynchronous/static.py
nyanger/asynchronous/log_writers/__init__.py
nyanger/asynchronous/log_writers/console_writer.py
nyanger/asynchronous/log_writers/file_writer.py
nyanger/process/__init__.py
nyanger/process/nyan.py
nyanger/process/static.py
nyanger/process/log_writers/__init__.py
nyanger/process/log_writers/console_writer.py
nyanger/process/log_writers/file_writer.py
nyanger/simple/__init__.py
nyanger/simple/nyan.py
nyanger/simple/static.py
nyanger/simple/log_writers/__init__.py
nyanger/simple/log_writers/console_writer.py
nyanger/simple/log_writers/file_writer.py
nyanger-0.9.2.dist-info/METADATA
nyanger-0.9.2.dist-info/WHEEL
nyanger-0.9.2.dist-info/licenses/LICENSE
nyanger-0.9.2.dist-info/RECORD
