Metadata-Version: 2.4
Name: nyanger
Version: 0.9.2
Summary: Simple logger. Simple to use. Simple to modify.
Project-URL: Homepage, https://github.com/Nyanraltotlapun/Nyanger
Project-URL: Issues, https://github.com/Nyanraltotlapun/Nyanger/issues
Author-email: Kirill Harmatulla Shakirov <kirill.shakirov@protonmail.com>
License-File: LICENSE
Classifier: Intended Audience :: Developers
Classifier: Intended Audience :: Education
Classifier: License :: OSI Approved :: GNU General Public License v3 (GPLv3)
Classifier: Operating System :: OS Independent
Classifier: Programming Language :: Python :: 3
Requires-Python: >=3.8
